[
  {
    "Job ID": "00326229-1",
    "Title": "ビッドマネジャー（アナリスト - シニア・アナリスト）- コーポレート職",
    "Location": "",
    "Posted Date": "2026-07-17T00:00:00Z",
    "Job URL": "https://accenture.wd103.myworkdayjobs.com/en-US/AccentureCareers/job/Tokyo/--------_R00326229-1",
    "External Path": "/job/Tokyo/--------_R00326229-1",
    "Bullet Fields": [
      "R00326229",
      "Tokyo"
    ],
    "Requisition ID": "R00326229",
    "Scraped At": "2026-07-17T08:05:27Z",
    "Posted Date Original": "Posted Today"
  },
  {
    "Job ID": "00300204-1",
    "Title": "プライシング・アーキテクト 価格戦略担当（スペシャリスト - アソシエイトマネージャー）-コーポレート職",
    "Location": "",
    "Posted Date": "2026-07-17T00:00:00Z",
    "Job URL": "https://accenture.wd103.myworkdayjobs.com/en-US/AccentureCareers/job/Yokohama/--------_R00300204-1",
    "External Path": "/job/Yokohama/--------_R00300204-1",
    "Bullet Fields": [
      "R00300204",
      "Yokohama"
    ],
    "Requisition ID": "R00300204",
    "Scraped At": "2026-07-17T08:05:27Z",
    "Posted Date Original": "Posted Today"
  },
  {
    "Job ID": "00301230",
    "Title": "Network Ops Engineer",
    "Location": "",
    "Posted Date": "2026-07-17T00:00:00Z",
    "Job URL": "https://accenture.wd103.myworkdayjobs.com/en-US/AccentureCareers/job/Portsmouth/Network-Ops-Engineer_R00301230",
    "External Path": "/job/Portsmouth/Network-Ops-Engineer_R00301230",
    "Bullet Fields": [
      "R00301230",
      "Portsmouth"
    ],
    "Requisition ID": "R00301230",
    "Scraped At": "2026-07-17T08:05:27Z",
    "Posted Date Original": "Posted Today"
  },
  {
    "Job ID": "00250899-1",
    "Title": "コントラクト・マネジメント（アソシエイト・マネジャー） - コーポレート職",
    "Location": "",
    "Posted Date": "2026-07-17T00:00:00Z",
    "Job URL": "https://accenture.wd103.myworkdayjobs.com/en-US/AccentureCareers/job/Yokohama/-------_R00250899-1",
    "External Path": "/job/Yokohama/-------_R00250899-1",
    "Bullet Fields": [
      "R00250899",
      "Location Negotiable"
    ],
    "Requisition ID": "R00250899",
    "Scraped At": "2026-07-17T08:05:27Z",
    "Posted Date Original": "Posted Today"
  },
  {
    "Job ID": "00330607-1",
    "Title": "コントラクト・マネジメント（スペシャリスト） - コーポレート職",
    "Location": "",
    "Posted Date": "2026-07-17T00:00:00Z",
    "Job URL": "https://accenture.wd103.myworkdayjobs.com/en-US/AccentureCareers/job/Yokohama/------_R00330607-1",
    "External Path": "/job/Yokohama/------_R00330607-1",
    "Bullet Fields": [
      "R00330607",
      "Location Negotiable"
    ],
    "Requisition ID": "R00330607",
    "Scraped At": "2026-07-17T08:05:27Z",
    "Posted Date Original": "Posted Today"
  },
  {
    "Job ID": "00258110-1",
    "Title": "コントラクト・マネジメント（シニア・アナリスト） - コーポレート職",
    "Location": "",
    "Posted Date": "2026-07-17T00:00:00Z",
    "Job URL": "https://accenture.wd103.myworkdayjobs.com/en-US/AccentureCareers/job/Yokohama/-------_R00258110-1",
    "External Path": "/job/Yokohama/-------_R00258110-1",
    "Bullet Fields": [
      "R00258110",
      "Yokohama"
    ],
    "Requisition ID": "R00258110",
    "Scraped At": "2026-07-17T08:05:27Z",
    "Posted Date Original": "Posted Today"
  },
  {
    "Job ID": "00342557-1",
    "Title": "営業法務（マネジャー）- コーポレート職",
    "Location": "",
    "Posted Date": "2026-07-17T00:00:00Z",
    "Job URL": "https://accenture.wd103.myworkdayjobs.com/en-US/AccentureCareers/job/Yokohama/----_R00342557-1",
    "External Path": "/job/Yokohama/----_R00342557-1",
    "Bullet Fields": [
      "R00342557",
      "Yokohama"
    ],
    "Requisition ID": "R00342557",
    "Scraped At": "2026-07-17T08:05:27Z",
    "Posted Date Original": "Posted Today"
  },
  {
    "Job ID": "00340986-1",
    "Title": "営業法務（アソシエイト・マネジャー ）- コーポレート職",
    "Location": "",
    "Posted Date": "2026-07-17T00:00:00Z",
    "Job URL": "https://accenture.wd103.myworkdayjobs.com/en-US/AccentureCareers/job/Yokohama/------_R00340986-1",
    "External Path": "/job/Yokohama/------_R00340986-1",
    "Bullet Fields": [
      "R00340986",
      "Yokohama"
    ],
    "Requisition ID": "R00340986",
    "Scraped At": "2026-07-17T08:05:27Z",
    "Posted Date Original": "Posted Today"
  },
  {
    "Job ID": "00341293-1",
    "Title": "法務・コンプライアンス担当（シニア・アナリスト）-コーポレート職",
    "Location": "",
    "Posted Date": "2026-07-17T00:00:00Z",
    "Job URL": "https://accenture.wd103.myworkdayjobs.com/en-US/AccentureCareers/job/Yokohama/-----_R00341293-1",
    "External Path": "/job/Yokohama/-----_R00341293-1",
    "Bullet Fields": [
      "R00341293",
      "Yokohama"
    ],
    "Requisition ID": "R00341293",
    "Scraped At": "2026-07-17T08:05:27Z",
    "Posted Date Original": "Posted Today"
  },
  {
    "Job ID": "00343113-2",
    "Title": "SAP Transportation Management Consultant",
    "Location": "",
    "Posted Date": "2026-07-17T00:00:00Z",
    "Job URL": "https://accenture.wd103.myworkdayjobs.com/en-US/AccentureCareers/job/Auckland/SAP-Transportation-Management-Consultant_R00343113-2",
    "External Path": "/job/Auckland/SAP-Transportation-Management-Consultant_R00343113-2",
    "Bullet Fields": [
      "R00343113",
      "Location Negotiable"
    ],
    "Requisition ID": "R00343113",
    "Scraped At": "2026-07-17T08:05:27Z",
    "Posted Date Original": "Posted Today"
  },
  {
    "Job ID": "00343111",
    "Title": "SAP SD (Sales & Distribution) Functional Consultant",
    "Location": "",
    "Posted Date": "2026-07-17T00:00:00Z",
    "Job URL": "https://accenture.wd103.myworkdayjobs.com/en-US/AccentureCareers/job/Auckland/SAP-SD--Sales---Distribution--Functional-Consultant_R00343111",
    "External Path": "/job/Auckland/SAP-SD--Sales---Distribution--Functional-Consultant_R00343111",
    "Bullet Fields": [
      "R00343111",
      "Location Negotiable"
    ],
    "Requisition ID": "R00343111",
    "Scraped At": "2026-07-17T08:05:27Z",
    "Posted Date Original": "Posted Today"
  },
  {
    "Job ID": "00265608-1",
    "Title": "コントラクト・マネジメント（マネジャー） - コーポレート職",
    "Location": "",
    "Posted Date": "2026-07-17T00:00:00Z",
    "Job URL": "https://accenture.wd103.myworkdayjobs.com/en-US/AccentureCareers/job/Yokohama/------_R00265608-1",
    "External Path": "/job/Yokohama/------_R00265608-1",
    "Bullet Fields": [
      "R00265608",
      "Location Negotiable"
    ],
    "Requisition ID": "R00265608",
    "Scraped At": "2026-07-17T08:05:27Z",
    "Posted Date Original": "Posted Today"
  },
  {
    "Job ID": "00338915-1",
    "Title": "Corporate Investigations Counsel Associate Manager",
    "Location": "",
    "Posted Date": "2026-07-16T00:00:00Z",
    "Job URL": "https://accenture.wd103.myworkdayjobs.com/en-US/AccentureCareers/job/Sao-Paulo-Torre-Paineira/Corporate-Investigations-Counsel-Associate-Manager_R00338915-1",
    "External Path": "/job/Sao-Paulo-Torre-Paineira/Corporate-Investigations-Counsel-Associate-Manager_R00338915-1",
    "Bullet Fields": [
      "R00338915",
      "Sao Paulo, Torre Paineira"
    ],
    "Requisition ID": "R00338915",
    "Scraped At": "2026-07-17T08:05:27Z",
    "Posted Date Original": "Posted Yesterday"
  },
  {
    "Job ID": "00314098",
    "Title": "Analista de Contas a Pagar - Híbrido",
    "Location": "",
    "Posted Date": "2026-07-16T00:00:00Z",
    "Job URL": "https://accenture.wd103.myworkdayjobs.com/en-US/AccentureCareers/job/Rio-de-Janeiro---Macae/Analista-de-Contas-a-Pagar-Jnior_R00314098",
    "External Path": "/job/Rio-de-Janeiro---Macae/Analista-de-Contas-a-Pagar-Jnior_R00314098",
    "Bullet Fields": [
      "R00314098",
      "Location Negotiable"
    ],
    "Requisition ID": "R00314098",
    "Scraped At": "2026-07-17T08:05:27Z",
    "Posted Date Original": "Posted Yesterday"
  },
  {
    "Job ID": "00338887",
    "Title": "Labor and Employment Counsel Associate Manager",
    "Location": "",
    "Posted Date": "2026-07-16T00:00:00Z",
    "Job URL": "https://accenture.wd103.myworkdayjobs.com/en-US/AccentureCareers/job/Sao-Paulo-Torre-Paineira/Labor-and-Employment-Counsel-Associate-Manager_R00338887",
    "External Path": "/job/Sao-Paulo-Torre-Paineira/Labor-and-Employment-Counsel-Associate-Manager_R00338887",
    "Bullet Fields": [
      "R00338887",
      "Sao Paulo, Torre Paineira"
    ],
    "Requisition ID": "R00338887",
    "Scraped At": "2026-07-17T08:05:27Z",
    "Posted Date Original": "Posted Yesterday"
  },
  {
    "Job ID": "00344193",
    "Title": "HR Generalist with English",
    "Location": "",
    "Posted Date": "2026-07-16T00:00:00Z",
    "Job URL": "https://accenture.wd103.myworkdayjobs.com/en-US/AccentureCareers/job/Bucharest-Westgate-Park---Bldg-H1/HR-Generalist-with-English_R00344193",
    "External Path": "/job/Bucharest-Westgate-Park---Bldg-H1/HR-Generalist-with-English_R00344193",
    "Bullet Fields": [
      "R00344193",
      "Bucharest, Westgate Park - Bldg H1"
    ],
    "Requisition ID": "R00344193",
    "Scraped At": "2026-07-17T08:05:27Z",
    "Posted Date Original": "Posted Yesterday"
  },
  {
    "Job ID": "00323136",
    "Title": "Analista Contábil Sênior - Híbrido",
    "Location": "",
    "Posted Date": "2026-07-16T00:00:00Z",
    "Job URL": "https://accenture.wd103.myworkdayjobs.com/en-US/AccentureCareers/job/Nova-Lima-Shopping-Alta-Vila/Analista-Contbil-Snior_R00323136",
    "External Path": "/job/Nova-Lima-Shopping-Alta-Vila/Analista-Contbil-Snior_R00323136",
    "Bullet Fields": [
      "R00323136",
      "Location Negotiable"
    ],
    "Requisition ID": "R00323136",
    "Scraped At": "2026-07-17T08:05:27Z",
    "Posted Date Original": "Posted Yesterday"
  },
  {
    "Job ID": "00291576-1",
    "Title": "Life Sciences Commercial/CRM Consultant",
    "Location": "",
    "Posted Date": "2026-07-16T00:00:00Z",
    "Job URL": "https://accenture.wd103.myworkdayjobs.com/en-US/AccentureCareers/job/Belen-La-Ribera/Strategy---Consulting---Global-Network---Products---Life-Sciences-Commercial-Consultant_R00291576-1",
    "External Path": "/job/Belen-La-Ribera/Strategy---Consulting---Global-Network---Products---Life-Sciences-Commercial-Consultant_R00291576-1",
    "Bullet Fields": [
      "R00291576",
      "Belen, La Ribera"
    ],
    "Requisition ID": "R00291576",
    "Scraped At": "2026-07-17T08:05:27Z",
    "Posted Date Original": "Posted Yesterday"
  },
  {
    "Job ID": "00339499",
    "Title": "IT Business Analyst",
    "Location": "",
    "Posted Date": "2026-07-16T00:00:00Z",
    "Job URL": "https://accenture.wd103.myworkdayjobs.com/en-US/AccentureCareers/job/Ebene/IT-Business-Analyst_R00339499",
    "External Path": "/job/Ebene/IT-Business-Analyst_R00339499",
    "Bullet Fields": [
      "R00339499",
      "Ebene"
    ],
    "Requisition ID": "R00339499",
    "Scraped At": "2026-07-17T08:05:27Z",
    "Posted Date Original": "Posted Yesterday"
  },
  {
    "Job ID": "00306597",
    "Title": "Cloud Operations Engineer",
    "Location": "",
    "Posted Date": "2026-07-16T00:00:00Z",
    "Job URL": "https://accenture.wd103.myworkdayjobs.com/en-US/AccentureCareers/job/Cheltenham/Cloud-Operations-Engineer_R00306597",
    "External Path": "/job/Cheltenham/Cloud-Operations-Engineer_R00306597",
    "Bullet Fields": [
      "R00306597",
      "Cheltenham"
    ],
    "Requisition ID": "R00306597",
    "Scraped At": "2026-07-17T08:05:27Z",
    "Posted Date Original": "Posted Yesterday"
  }
]