[
  {
    "Job ID": "00280101",
    "Title": "Contract Associate Manager - NRR 4125",
    "Location": "",
    "Posted Date": "2025-08-01T00:00:00Z",
    "Job URL": "https://accenture.wd103.myworkdayjobs.com/en-US/AccentureCareers/job/Canberra-65-Canberra-Avenue-Bldg/Contract-Associate-Manager---NRR-4125_R00280101",
    "External Path": "/job/Canberra-65-Canberra-Avenue-Bldg/Contract-Associate-Manager---NRR-4125_R00280101",
    "Bullet Fields": [
      "R00280101",
      "Canberra, 65 Canberra Avenue Bldg"
    ],
    "Requisition ID": "R00280101",
    "Scraped At": "2025-08-01T06:31:30Z",
    "Posted Date Original": "Posted Today"
  },
  {
    "Job ID": "00280060",
    "Title": "Contact Center AI Solution Consultant",
    "Location": "",
    "Posted Date": "2025-08-01T00:00:00Z",
    "Job URL": "https://accenture.wd103.myworkdayjobs.com/en-US/AccentureCareers/job/Taguig/Customer-Platform---CCAI-Consultant_R00280060",
    "External Path": "/job/Taguig/Customer-Platform---CCAI-Consultant_R00280060",
    "Bullet Fields": [
      "R00280060",
      "Taguig"
    ],
    "Requisition ID": "R00280060",
    "Scraped At": "2025-08-01T06:31:30Z",
    "Posted Date Original": "Posted Today"
  },
  {
    "Job ID": "00279799",
    "Title": "Contact Center AI Solution Consulting Manager",
    "Location": "",
    "Posted Date": "2025-08-01T00:00:00Z",
    "Job URL": "https://accenture.wd103.myworkdayjobs.com/en-US/AccentureCareers/job/Taguig/Customer-Platform---CCAI-Management-Consulting-Manager_R00279799",
    "External Path": "/job/Taguig/Customer-Platform---CCAI-Management-Consulting-Manager_R00279799",
    "Bullet Fields": [
      "R00279799",
      "Taguig"
    ],
    "Requisition ID": "R00279799",
    "Scraped At": "2025-08-01T06:31:30Z",
    "Posted Date Original": "Posted Today"
  },
  {
    "Job ID": "00252994",
    "Title": "Management Consulting Senior Manager - S&C Global Network (CMT - Semiconductor HT)",
    "Location": "",
    "Posted Date": "2025-08-01T00:00:00Z",
    "Job URL": "https://accenture.wd103.myworkdayjobs.com/en-US/AccentureCareers/job/Kuala-Lumpur-Exchange-106/Management-Consulting-Manager---S-C-Global-Network--Comms---Media-_R00252994",
    "External Path": "/job/Kuala-Lumpur-Exchange-106/Management-Consulting-Manager---S-C-Global-Network--Comms---Media-_R00252994",
    "Bullet Fields": [
      "R00252994",
      "Kuala Lumpur, Exchange 106"
    ],
    "Requisition ID": "R00252994",
    "Scraped At": "2025-08-01T06:31:30Z",
    "Posted Date Original": "Posted Today"
  },
  {
    "Job ID": "00265612-1",
    "Title": "Contract Manager",
    "Location": "",
    "Posted Date": "2025-08-01T00:00:00Z",
    "Job URL": "https://accenture.wd103.myworkdayjobs.com/en-US/AccentureCareers/job/Canberra/Contract-Manager_R00265612-1",
    "External Path": "/job/Canberra/Contract-Manager_R00265612-1",
    "Bullet Fields": [
      "R00265612",
      "Location Negotiable"
    ],
    "Requisition ID": "R00265612",
    "Scraped At": "2025-08-01T06:31:30Z",
    "Posted Date Original": "Posted Today"
  },
  {
    "Job ID": "00274746",
    "Title": "Team Lead - Princing",
    "Location": "",
    "Posted Date": "2025-08-01T00:00:00Z",
    "Job URL": "https://accenture.wd103.myworkdayjobs.com/en-US/AccentureCareers/job/San-Jose-Plaza-Real-Cariari/Team-Lead---Princing_R00274746",
    "External Path": "/job/San-Jose-Plaza-Real-Cariari/Team-Lead---Princing_R00274746",
    "Bullet Fields": [
      "R00274746",
      "San Jose, Plaza Real Cariari"
    ],
    "Requisition ID": "R00274746",
    "Scraped At": "2025-08-01T06:31:30Z",
    "Posted Date Original": "Posted Today"
  },
  {
    "Job ID": "00279512",
    "Title": "Contracting Specialist",
    "Location": "",
    "Posted Date": "2025-08-01T00:00:00Z",
    "Job URL": "https://accenture.wd103.myworkdayjobs.com/en-US/AccentureCareers/job/Mexico-City/Contracting-Specialist_R00279512",
    "External Path": "/job/Mexico-City/Contracting-Specialist_R00279512",
    "Bullet Fields": [
      "R00279512",
      "Mexico City"
    ],
    "Requisition ID": "R00279512",
    "Scraped At": "2025-08-01T06:31:30Z",
    "Posted Date Original": "Posted Today"
  },
  {
    "Job ID": "00279884-1",
    "Title": "Contracting Associate Manager",
    "Location": "",
    "Posted Date": "2025-08-01T00:00:00Z",
    "Job URL": "https://accenture.wd103.myworkdayjobs.com/en-US/AccentureCareers/job/Mexico-City/Contracting-Associate-Manager_R00279884-1",
    "External Path": "/job/Mexico-City/Contracting-Associate-Manager_R00279884-1",
    "Bullet Fields": [
      "R00279884",
      "Mexico City"
    ],
    "Requisition ID": "R00279884",
    "Scraped At": "2025-08-01T06:31:30Z",
    "Posted Date Original": "Posted Today"
  },
  {
    "Job ID": "00209929",
    "Title": "GN - SONG - Service – Nice CXone- Analyst",
    "Location": "",
    "Posted Date": "2025-08-01T00:00:00Z",
    "Job URL": "https://accenture.wd103.myworkdayjobs.com/en-US/AccentureCareers/job/Chennai-CDC5B/GN---SONG---MT---Marketing-Automation-B2C--Consultant_R00209929",
    "External Path": "/job/Chennai-CDC5B/GN---SONG---MT---Marketing-Automation-B2C--Consultant_R00209929",
    "Bullet Fields": [
      "R00209929",
      "Chennai, Cdc5B"
    ],
    "Requisition ID": "R00209929",
    "Scraped At": "2025-08-01T06:31:30Z",
    "Posted Date Original": "Posted Today"
  },
  {
    "Job ID": "00211102",
    "Title": "GN - SONG - Service - Nice CXone- Consultant",
    "Location": "",
    "Posted Date": "2025-08-01T00:00:00Z",
    "Job URL": "https://accenture.wd103.myworkdayjobs.com/en-US/AccentureCareers/job/Bengaluru-BDC7A/GN---SONG---MT---CDP-Manager_R00211102",
    "External Path": "/job/Bengaluru-BDC7A/GN---SONG---MT---CDP-Manager_R00211102",
    "Bullet Fields": [
      "R00211102",
      "Bengaluru, Bdc7A"
    ],
    "Requisition ID": "R00211102",
    "Scraped At": "2025-08-01T06:31:30Z",
    "Posted Date Original": "Posted Today"
  },
  {
    "Job ID": "91466-1",
    "Title": "GN - SONG - Service - Nice CXOne - Manager",
    "Location": "",
    "Posted Date": "2025-08-01T00:00:00Z",
    "Job URL": "https://accenture.wd103.myworkdayjobs.com/en-US/AccentureCareers/job/Hyderabad-HDC2A/GN---SONG---MT---Insights-as-a-Service---Consultant_R91466-1",
    "External Path": "/job/Hyderabad-HDC2A/GN---SONG---MT---Insights-as-a-Service---Consultant_R91466-1",
    "Bullet Fields": [
      "R91466",
      "Hyderabad, Hdc2A"
    ],
    "Requisition ID": "R91466",
    "Scraped At": "2025-08-01T06:31:30Z",
    "Posted Date Original": "Posted Today"
  },
  {
    "Job ID": "00198848",
    "Title": "GN - SONG - Service - Nice CXOne - Senior Manager",
    "Location": "",
    "Posted Date": "2025-08-01T00:00:00Z",
    "Job URL": "https://accenture.wd103.myworkdayjobs.com/en-US/AccentureCareers/job/Pune-PDC2C/GN---SONG---ACE---NICE-Cxone-Manager_R00198848",
    "External Path": "/job/Pune-PDC2C/GN---SONG---ACE---NICE-Cxone-Manager_R00198848",
    "Bullet Fields": [
      "R00198848",
      "Pune, Pdc2C"
    ],
    "Requisition ID": "R00198848",
    "Scraped At": "2025-08-01T06:31:30Z",
    "Posted Date Original": "Posted Today"
  },
  {
    "Job ID": "00237564-14",
    "Title": "S&C-GN - Platforms- Oracle(SAP)_CL6",
    "Location": "",
    "Posted Date": "2025-08-01T00:00:00Z",
    "Job URL": "https://accenture.wd103.myworkdayjobs.com/en-US/AccentureCareers/job/Bengaluru-BDC14A/GN-SAP-Platform---CMT---Delivery-Lead--CL6_R00237564-14",
    "External Path": "/job/Bengaluru-BDC14A/GN-SAP-Platform---CMT---Delivery-Lead--CL6_R00237564-14",
    "Bullet Fields": [
      "R00237564",
      "Bengaluru, Bdc14A"
    ],
    "Requisition ID": "R00237564",
    "Scraped At": "2025-08-01T06:31:30Z",
    "Posted Date Original": "Posted Today"
  },
  {
    "Job ID": "00237438-25",
    "Title": "S&C-GN - Industry Architect- Platforms (SAP)_CL6",
    "Location": "",
    "Posted Date": "2025-08-01T00:00:00Z",
    "Job URL": "https://accenture.wd103.myworkdayjobs.com/en-US/AccentureCareers/job/Mumbai-MC1-Building-NonSTPI/GN-SAP-Platform---Products---Delivery-Lead--CL6_R00237438-25",
    "External Path": "/job/Mumbai-MC1-Building-NonSTPI/GN-SAP-Platform---Products---Delivery-Lead--CL6_R00237438-25",
    "Bullet Fields": [
      "R00237438",
      "Mumbai, Mc1 Building, Nonstpi"
    ],
    "Requisition ID": "R00237438",
    "Scraped At": "2025-08-01T06:31:30Z",
    "Posted Date Original": "Posted Today"
  },
  {
    "Job ID": "00237441-56",
    "Title": "S&C-GN - Industry Architect- Platforms (SAP)_CL6",
    "Location": "",
    "Posted Date": "2025-08-01T00:00:00Z",
    "Job URL": "https://accenture.wd103.myworkdayjobs.com/en-US/AccentureCareers/job/Chennai-CC1A-NonSTPI/GN-SAP-Platform---Products---Delivery-Lead--CL6_R00237441-56",
    "External Path": "/job/Chennai-CC1A-NonSTPI/GN-SAP-Platform---Products---Delivery-Lead--CL6_R00237441-56",
    "Bullet Fields": [
      "R00237441",
      "Chennai, Cc1A, Nonstpi"
    ],
    "Requisition ID": "R00237441",
    "Scraped At": "2025-08-01T06:31:30Z",
    "Posted Date Original": "Posted Today"
  },
  {
    "Job ID": "00269842",
    "Title": "Sales Ops - Order Management",
    "Location": "",
    "Posted Date": "2025-08-01T00:00:00Z",
    "Job URL": "https://accenture.wd103.myworkdayjobs.com/en-US/AccentureCareers/job/Heredia/Sales-Ops-Order-Management---Senior-Analyst_R00269842",
    "External Path": "/job/Heredia/Sales-Ops-Order-Management---Senior-Analyst_R00269842",
    "Bullet Fields": [
      "R00269842",
      "Heredia"
    ],
    "Requisition ID": "R00269842",
    "Scraped At": "2025-08-01T06:31:30Z",
    "Posted Date Original": "Posted Today"
  },
  {
    "Job ID": "00280273",
    "Title": "Inside Sales (English speaker)",
    "Location": "",
    "Posted Date": "2025-08-01T00:00:00Z",
    "Job URL": "https://accenture.wd103.myworkdayjobs.com/en-US/AccentureCareers/job/Malaga/Inside-Sales--English-speaker-_R00280273",
    "External Path": "/job/Malaga/Inside-Sales--English-speaker-_R00280273",
    "Bullet Fields": [
      "R00280273",
      "Malaga"
    ],
    "Requisition ID": "R00280273",
    "Scraped At": "2025-08-01T06:31:30Z",
    "Posted Date Original": "Posted Today"
  },
  {
    "Job ID": "00271864",
    "Title": "Workday HCM Lead (all genders)",
    "Location": "",
    "Posted Date": "2025-08-01T00:00:00Z",
    "Job URL": "https://accenture.wd103.myworkdayjobs.com/en-US/AccentureCareers/job/Berlin/Workday-Reporting-Lead--all-genders-_R00271864",
    "External Path": "/job/Berlin/Workday-Reporting-Lead--all-genders-_R00271864",
    "Bullet Fields": [
      "R00271864",
      "Location Negotiable"
    ],
    "Requisition ID": "R00271864",
    "Scraped At": "2025-08-01T06:31:30Z",
    "Posted Date Original": "Posted Today"
  },
  {
    "Job ID": "00220886",
    "Title": "SAP SuccessFactors Consultant - Manager",
    "Location": "",
    "Posted Date": "2025-08-01T00:00:00Z",
    "Job URL": "https://accenture.wd103.myworkdayjobs.com/en-US/AccentureCareers/job/Amsterdam-Gustav-Mahlerplein-90/SAP-SuccesFactors-Consultant_R00220886",
    "External Path": "/job/Amsterdam-Gustav-Mahlerplein-90/SAP-SuccesFactors-Consultant_R00220886",
    "Bullet Fields": [
      "R00220886",
      "Amsterdam, Gustav Mahlerplein 90"
    ],
    "Requisition ID": "R00220886",
    "Scraped At": "2025-08-01T06:31:30Z",
    "Posted Date Original": "Posted Today"
  },
  {
    "Job ID": "00280097",
    "Title": "Contract Specialist - NRR 4096",
    "Location": "",
    "Posted Date": "2025-08-01T00:00:00Z",
    "Job URL": "https://accenture.wd103.myworkdayjobs.com/en-US/AccentureCareers/job/Melbourne-161-Collins-Street-Level-5/Contract-Specialist---NRR-4096_R00280097",
    "External Path": "/job/Melbourne-161-Collins-Street-Level-5/Contract-Specialist---NRR-4096_R00280097",
    "Bullet Fields": [
      "R00280097",
      "Melbourne, 161 Collins Street, Level 5"
    ],
    "Requisition ID": "R00280097",
    "Scraped At": "2025-08-01T06:31:30Z",
    "Posted Date Original": "Posted Today"
  }
]