[
  {
    "Job ID": "00214621",
    "Title": "GN Industry Utility SAP DM Consultant",
    "Location": "",
    "Posted Date": "2025-11-23T00:00:00Z",
    "Job URL": "https://accenture.wd103.myworkdayjobs.com/en-US/AccentureCareers/job/Bengaluru-BDC7C/GN---Industry---Energy---Strategy-Analyst_R00214621",
    "External Path": "/job/Bengaluru-BDC7C/GN---Industry---Energy---Strategy-Analyst_R00214621",
    "Bullet Fields": [
      "R00214621",
      "Bengaluru, Bdc7C"
    ],
    "Requisition ID": "R00214621",
    "Scraped At": "2025-11-23T06:25:46Z",
    "Posted Date Original": "Posted Today"
  },
  {
    "Job ID": "00298568",
    "Title": "Operador de call center - E-commerce (Híbrido)",
    "Location": "",
    "Posted Date": "2025-11-22T00:00:00Z",
    "Job URL": "https://accenture.wd103.myworkdayjobs.com/en-US/AccentureCareers/job/Barueri-Green-Valley-Andromeda/Operador-de-call-center---E-commerce--Hbrido-_R00298568",
    "External Path": "/job/Barueri-Green-Valley-Andromeda/Operador-de-call-center---E-commerce--Hbrido-_R00298568",
    "Bullet Fields": [
      "R00298568",
      "Barueri, Green Valley, Andromeda"
    ],
    "Requisition ID": "R00298568",
    "Scraped At": "2025-11-23T06:25:46Z",
    "Posted Date Original": "Posted Yesterday"
  },
  {
    "Job ID": "00298399",
    "Title": "Deal Structuring & Pricing - Pricing Architect",
    "Location": "",
    "Posted Date": "2025-11-22T00:00:00Z",
    "Job URL": "https://accenture.wd103.myworkdayjobs.com/en-US/AccentureCareers/job/Amsterdam/Deal-Structuring---Pricing---Pricing-Architect_R00298399",
    "External Path": "/job/Amsterdam/Deal-Structuring---Pricing---Pricing-Architect_R00298399",
    "Bullet Fields": [
      "R00298399",
      "Amsterdam"
    ],
    "Requisition ID": "R00298399",
    "Scraped At": "2025-11-23T06:25:46Z",
    "Posted Date Original": "Posted Yesterday"
  },
  {
    "Job ID": "00281179",
    "Title": "Treinador de Atendimento e Operações Sênior - Espanhol e Inglês",
    "Location": "",
    "Posted Date": "2025-11-22T00:00:00Z",
    "Job URL": "https://accenture.wd103.myworkdayjobs.com/en-US/AccentureCareers/job/Nova-Lima-Shopping-Alta-Vila/Treinador-de-Atendimento-e-Operaes-Snior---Espanhol_R00281179",
    "External Path": "/job/Nova-Lima-Shopping-Alta-Vila/Treinador-de-Atendimento-e-Operaes-Snior---Espanhol_R00281179",
    "Bullet Fields": [
      "R00281179",
      "Nova Lima, Shopping Alta Vila"
    ],
    "Requisition ID": "R00281179",
    "Scraped At": "2025-11-23T06:25:46Z",
    "Posted Date Original": "Posted Yesterday"
  },
  {
    "Job ID": "00259512",
    "Title": "S&C GN-Industry Strategy-Life Sciences-Analyst",
    "Location": "",
    "Posted Date": "2025-11-22T00:00:00Z",
    "Job URL": "https://accenture.wd103.myworkdayjobs.com/en-US/AccentureCareers/job/Mumbai-MC1-Building-NonSTPI/S-C-GN-Industry-Strategy-Life-Sciences-Analyst_R00259512",
    "External Path": "/job/Mumbai-MC1-Building-NonSTPI/S-C-GN-Industry-Strategy-Life-Sciences-Analyst_R00259512",
    "Bullet Fields": [
      "R00259512",
      "Mumbai, Mc1 Building, Nonstpi"
    ],
    "Requisition ID": "R00259512",
    "Scraped At": "2025-11-23T06:25:46Z",
    "Posted Date Original": "Posted Yesterday"
  },
  {
    "Job ID": "00285064",
    "Title": "Technology Consulting Intern Health & Public Service",
    "Location": "",
    "Posted Date": "2025-11-22T00:00:00Z",
    "Job URL": "https://accenture.wd103.myworkdayjobs.com/en-US/AccentureCareers/job/Amsterdam/Technology-Consulting-Intern-Health---Public-Service_R00285064",
    "External Path": "/job/Amsterdam/Technology-Consulting-Intern-Health---Public-Service_R00285064",
    "Bullet Fields": [
      "R00285064",
      "Amsterdam"
    ],
    "Requisition ID": "R00285064",
    "Scraped At": "2025-11-23T06:25:46Z",
    "Posted Date Original": "Posted Yesterday"
  },
  {
    "Job ID": "00289973",
    "Title": "HR Transformation Consultant",
    "Location": "",
    "Posted Date": "2025-11-22T00:00:00Z",
    "Job URL": "https://accenture.wd103.myworkdayjobs.com/en-US/AccentureCareers/job/London/HR-Transformation-Consultant_R00289973",
    "External Path": "/job/London/HR-Transformation-Consultant_R00289973",
    "Bullet Fields": [
      "R00289973",
      "London"
    ],
    "Requisition ID": "R00289973",
    "Scraped At": "2025-11-23T06:25:46Z",
    "Posted Date Original": "Posted Yesterday"
  },
  {
    "Job ID": "00287644",
    "Title": "Oracle Integration Cloud Architect",
    "Location": "",
    "Posted Date": "2025-11-22T00:00:00Z",
    "Job URL": "https://accenture.wd103.myworkdayjobs.com/en-US/AccentureCareers/job/London/Oracle-Recruitment-Consultant_R00287644",
    "External Path": "/job/London/Oracle-Recruitment-Consultant_R00287644",
    "Bullet Fields": [
      "R00287644",
      "Location Negotiable"
    ],
    "Requisition ID": "R00287644",
    "Scraped At": "2025-11-23T06:25:46Z",
    "Posted Date Original": "Posted Yesterday"
  },
  {
    "Job ID": "00288274-1",
    "Title": "Management Consulting Manager - Utilities",
    "Location": "",
    "Posted Date": "2025-11-22T00:00:00Z",
    "Job URL": "https://accenture.wd103.myworkdayjobs.com/en-US/AccentureCareers/job/London/Management-Consulting-Manager---Utilities-Energy-Transition-Manager_R00288274-1",
    "External Path": "/job/London/Management-Consulting-Manager---Utilities-Energy-Transition-Manager_R00288274-1",
    "Bullet Fields": [
      "R00288274",
      "London"
    ],
    "Requisition ID": "R00288274",
    "Scraped At": "2025-11-23T06:25:46Z",
    "Posted Date Original": "Posted Yesterday"
  },
  {
    "Job ID": "00217646",
    "Title": "GN - SONG - MT - Salesforce Marketing Cloud - Associate Director",
    "Location": "",
    "Posted Date": "2025-11-22T00:00:00Z",
    "Job URL": "https://accenture.wd103.myworkdayjobs.com/en-US/AccentureCareers/job/Hyderabad-HDC2A/GN--SONG---MT---Hyper-personalization--CVM-Consultant_R00217646",
    "External Path": "/job/Hyderabad-HDC2A/GN--SONG---MT---Hyper-personalization--CVM-Consultant_R00217646",
    "Bullet Fields": [
      "R00217646",
      "Hyderabad, Hdc2A"
    ],
    "Requisition ID": "R00217646",
    "Scraped At": "2025-11-23T06:25:46Z",
    "Posted Date Original": "Posted Yesterday"
  },
  {
    "Job ID": "00291867",
    "Title": "Total Rewards Specialist",
    "Location": "",
    "Posted Date": "2025-11-22T00:00:00Z",
    "Job URL": "https://accenture.wd103.myworkdayjobs.com/en-US/AccentureCareers/job/Oslo/Total-Rewards-Specialist_R00291867",
    "External Path": "/job/Oslo/Total-Rewards-Specialist_R00291867",
    "Bullet Fields": [
      "R00291867",
      "Oslo"
    ],
    "Requisition ID": "R00291867",
    "Scraped At": "2025-11-23T06:25:46Z",
    "Posted Date Original": "Posted Yesterday"
  },
  {
    "Job ID": "00298302",
    "Title": "Coordinador de Seguridad y Salud (varias localizaciones España)",
    "Location": "",
    "Posted Date": "2025-11-21T00:00:00Z",
    "Job URL": "https://accenture.wd103.myworkdayjobs.com/en-US/AccentureCareers/job/Valencia/Coordinador-de-Seguridad-y-Salud--varias-localizaciones-Espaa-_R00298302",
    "External Path": "/job/Valencia/Coordinador-de-Seguridad-y-Salud--varias-localizaciones-Espaa-_R00298302",
    "Bullet Fields": [
      "R00298302",
      "Location Negotiable"
    ],
    "Requisition ID": "R00298302",
    "Scraped At": "2025-11-23T06:25:46Z",
    "Posted Date Original": "Posted 2 Days Ago"
  },
  {
    "Job ID": "00277029",
    "Title": "IT Delivery Lead Financial Services (all genders)",
    "Location": "",
    "Posted Date": "2025-11-21T00:00:00Z",
    "Job URL": "https://accenture.wd103.myworkdayjobs.com/en-US/AccentureCareers/job/Kronberg-Campus-Kronberg-1/IT-Delivery-Lead-Financial-Services--all-genders-_R00277029",
    "External Path": "/job/Kronberg-Campus-Kronberg-1/IT-Delivery-Lead-Financial-Services--all-genders-_R00277029",
    "Bullet Fields": [
      "R00277029",
      "Location Negotiable"
    ],
    "Requisition ID": "R00277029",
    "Scraped At": "2025-11-23T06:25:46Z",
    "Posted Date Original": "Posted 2 Days Ago"
  },
  {
    "Job ID": "00297895",
    "Title": "Mobility Analyst ASG Immigration - Alemán Avanzado",
    "Location": "",
    "Posted Date": "2025-11-21T00:00:00Z",
    "Job URL": "https://accenture.wd103.myworkdayjobs.com/en-US/AccentureCareers/job/Buenos-Aires/Mobility-Analyst-ASG-Immigration---Alemn-Avanzado_R00297895",
    "External Path": "/job/Buenos-Aires/Mobility-Analyst-ASG-Immigration---Alemn-Avanzado_R00297895",
    "Bullet Fields": [
      "R00297895",
      "Buenos Aires"
    ],
    "Requisition ID": "R00297895",
    "Scraped At": "2025-11-23T06:25:46Z",
    "Posted Date Original": "Posted 2 Days Ago"
  },
  {
    "Job ID": "00298222",
    "Title": "Mobile Test Automation Engineer (Java/Kotlin)",
    "Location": "",
    "Posted Date": "2025-11-21T00:00:00Z",
    "Job URL": "https://accenture.wd103.myworkdayjobs.com/en-US/AccentureCareers/job/Cluj-Napoca/Mobile-Test-Automation-Engineer--Java-Kotlin-_R00298222",
    "External Path": "/job/Cluj-Napoca/Mobile-Test-Automation-Engineer--Java-Kotlin-_R00298222",
    "Bullet Fields": [
      "R00298222",
      "Location Negotiable"
    ],
    "Requisition ID": "R00298222",
    "Scraped At": "2025-11-23T06:25:46Z",
    "Posted Date Original": "Posted 2 Days Ago"
  },
  {
    "Job ID": "00298201",
    "Title": "Lead Python AI Engineer",
    "Location": "",
    "Posted Date": "2025-11-21T00:00:00Z",
    "Job URL": "https://accenture.wd103.myworkdayjobs.com/en-US/AccentureCareers/job/Cluj-Napoca/Lead-Python-AI-Engineer_R00298201",
    "External Path": "/job/Cluj-Napoca/Lead-Python-AI-Engineer_R00298201",
    "Bullet Fields": [
      "R00298201",
      "Location Negotiable"
    ],
    "Requisition ID": "R00298201",
    "Scraped At": "2025-11-23T06:25:46Z",
    "Posted Date Original": "Posted 2 Days Ago"
  },
  {
    "Job ID": "00289186",
    "Title": "Category Manager with French",
    "Location": "",
    "Posted Date": "2025-11-21T00:00:00Z",
    "Job URL": "https://accenture.wd103.myworkdayjobs.com/en-US/AccentureCareers/job/Warsaw/Category-Manager---Technology--Gallia-_R00289186",
    "External Path": "/job/Warsaw/Category-Manager---Technology--Gallia-_R00289186",
    "Bullet Fields": [
      "R00289186",
      "Warsaw"
    ],
    "Requisition ID": "R00289186",
    "Scraped At": "2025-11-23T06:25:46Z",
    "Posted Date Original": "Posted 2 Days Ago"
  },
  {
    "Job ID": "00298206-1",
    "Title": "Full Stack Developer – Java & Angular with Cloud Expertise",
    "Location": "",
    "Posted Date": "2025-11-21T00:00:00Z",
    "Job URL": "https://accenture.wd103.myworkdayjobs.com/en-US/AccentureCareers/job/Cluj-Napoca/Full-Stack-Developer---Java---Angular-with-Cloud-Expertise_R00298206-1",
    "External Path": "/job/Cluj-Napoca/Full-Stack-Developer---Java---Angular-with-Cloud-Expertise_R00298206-1",
    "Bullet Fields": [
      "R00298206",
      "Location Negotiable"
    ],
    "Requisition ID": "R00298206",
    "Scraped At": "2025-11-23T06:25:46Z",
    "Posted Date Original": "Posted 2 Days Ago"
  },
  {
    "Job ID": "00262444-104",
    "Title": "S&C GN - Tech Strategy & Advisory - SAP S/4 MDG- Senior Manager",
    "Location": "",
    "Posted Date": "2025-11-21T00:00:00Z",
    "Job URL": "https://accenture.wd103.myworkdayjobs.com/en-US/AccentureCareers/job/Mumbai-MC1-Building-NonSTPI/S-C-GN---Tech-Strategy---Advisory---SAP-S-4---SD---SCM---Senior-Manager_R00262444-104",
    "External Path": "/job/Mumbai-MC1-Building-NonSTPI/S-C-GN---Tech-Strategy---Advisory---SAP-S-4---SD---SCM---Senior-Manager_R00262444-104",
    "Bullet Fields": [
      "R00262444",
      "Mumbai, Mc1 Building, Nonstpi"
    ],
    "Requisition ID": "R00262444",
    "Scraped At": "2025-11-23T06:25:46Z",
    "Posted Date Original": "Posted 2 Days Ago"
  },
  {
    "Job ID": "00288019",
    "Title": "Customer Platforms Manager",
    "Location": "",
    "Posted Date": "2025-11-21T00:00:00Z",
    "Job URL": "https://accenture.wd103.myworkdayjobs.com/en-US/AccentureCareers/job/London/Customer-Platforms-Manager_R00288019",
    "External Path": "/job/London/Customer-Platforms-Manager_R00288019",
    "Bullet Fields": [
      "R00288019",
      "London"
    ],
    "Requisition ID": "R00288019",
    "Scraped At": "2025-11-23T06:25:46Z",
    "Posted Date Original": "Posted 2 Days Ago"
  }
]