[
  {
    "Job ID": "00277042-1",
    "Title": "Geographic Legal Counsel Specialist - NRR 3951",
    "Location": "",
    "Posted Date": "2025-07-29T00:00:00Z",
    "Job URL": "https://accenture.wd103.myworkdayjobs.com/en-US/AccentureCareers/job/Napoli/Geographic-Legal-Counsel-Specialist---NRR-3951_R00277042-1",
    "External Path": "/job/Napoli/Geographic-Legal-Counsel-Specialist---NRR-3951_R00277042-1",
    "Bullet Fields": [
      "R00277042",
      "Napoli"
    ],
    "Requisition ID": "R00277042",
    "Scraped At": "2025-07-29T06:29:01Z",
    "Posted Date Original": "Posted Today"
  },
  {
    "Job ID": "00274167",
    "Title": "Account Manager or Consultant - Social & Community",
    "Location": "",
    "Posted Date": "2025-07-29T00:00:00Z",
    "Job URL": "https://accenture.wd103.myworkdayjobs.com/en-US/AccentureCareers/job/Melbourne/Account-Manager_R00274167",
    "External Path": "/job/Melbourne/Account-Manager_R00274167",
    "Bullet Fields": [
      "R00274167",
      "Location Negotiable"
    ],
    "Requisition ID": "R00274167",
    "Scraped At": "2025-07-29T06:29:01Z",
    "Posted Date Original": "Posted Today"
  },
  {
    "Job ID": "00279567",
    "Title": "Sales Operations Analyst with Portuguese, Spanish and English",
    "Location": "",
    "Posted Date": "2025-07-29T00:00:00Z",
    "Job URL": "https://accenture.wd103.myworkdayjobs.com/en-US/AccentureCareers/job/Buenos-Aires/Sales-Operations-Analyst-with-Portuguese--Spanish-and-English_R00279567",
    "External Path": "/job/Buenos-Aires/Sales-Operations-Analyst-with-Portuguese--Spanish-and-English_R00279567",
    "Bullet Fields": [
      "R00279567",
      "Buenos Aires"
    ],
    "Requisition ID": "R00279567",
    "Scraped At": "2025-07-29T06:29:01Z",
    "Posted Date Original": "Posted Today"
  },
  {
    "Job ID": "00277897",
    "Title": "Strat Growth Init Counsel Manager - NRR 4043",
    "Location": "",
    "Posted Date": "2025-07-29T00:00:00Z",
    "Job URL": "https://accenture.wd103.myworkdayjobs.com/en-US/AccentureCareers/job/Buenos-Aires/Strat-Growth-Init-Counsel-Manager---NRR-4043_R00277897",
    "External Path": "/job/Buenos-Aires/Strat-Growth-Init-Counsel-Manager---NRR-4043_R00277897",
    "Bullet Fields": [
      "R00277897",
      "Location Negotiable"
    ],
    "Requisition ID": "R00277897",
    "Scraped At": "2025-07-29T06:29:01Z",
    "Posted Date Original": "Posted Today"
  },
  {
    "Job ID": "00279575",
    "Title": "Analista de Vendas Pleno Inglês e Espanhol avançados- Híbrido",
    "Location": "",
    "Posted Date": "2025-07-29T00:00:00Z",
    "Job URL": "https://accenture.wd103.myworkdayjobs.com/en-US/AccentureCareers/job/Sao-Paulo-Torre-Paineira/Analista-de-Vendas-Pleno-Ingls-e-Espanhol-avanados--Hbrido_R00279575",
    "External Path": "/job/Sao-Paulo-Torre-Paineira/Analista-de-Vendas-Pleno-Ingls-e-Espanhol-avanados--Hbrido_R00279575",
    "Bullet Fields": [
      "R00279575",
      "Sao Paulo, Torre Paineira"
    ],
    "Requisition ID": "R00279575",
    "Scraped At": "2025-07-29T06:29:01Z",
    "Posted Date Original": "Posted Today"
  },
  {
    "Job ID": "00279581",
    "Title": "HR Generalist Officer with German",
    "Location": "",
    "Posted Date": "2025-07-29T00:00:00Z",
    "Job URL": "https://accenture.wd103.myworkdayjobs.com/en-US/AccentureCareers/job/Bucharest-Westgate-Park---Bldg-H1/HR-Generalist-Officer-with-German_R00279581",
    "External Path": "/job/Bucharest-Westgate-Park---Bldg-H1/HR-Generalist-Officer-with-German_R00279581",
    "Bullet Fields": [
      "R00279581",
      "Location Negotiable"
    ],
    "Requisition ID": "R00279581",
    "Scraped At": "2025-07-29T06:29:01Z",
    "Posted Date Original": "Posted Today"
  },
  {
    "Job ID": "00268987",
    "Title": "Mobilization Manager",
    "Location": "",
    "Posted Date": "2025-07-29T00:00:00Z",
    "Job URL": "https://accenture.wd103.myworkdayjobs.com/en-US/AccentureCareers/job/London/Mobilization-Manager_R00268987",
    "External Path": "/job/London/Mobilization-Manager_R00268987",
    "Bullet Fields": [
      "R00268987",
      "London"
    ],
    "Requisition ID": "R00268987",
    "Scraped At": "2025-07-29T06:29:01Z",
    "Posted Date Original": "Posted Today"
  },
  {
    "Job ID": "91466-1",
    "Title": "GN - SONG - Service - Nice CX One - Manager",
    "Location": "",
    "Posted Date": "2025-07-29T00:00:00Z",
    "Job URL": "https://accenture.wd103.myworkdayjobs.com/en-US/AccentureCareers/job/Hyderabad-HDC2A/GN---SONG---MT---Insights-as-a-Service---Consultant_R91466-1",
    "External Path": "/job/Hyderabad-HDC2A/GN---SONG---MT---Insights-as-a-Service---Consultant_R91466-1",
    "Bullet Fields": [
      "R91466",
      "Hyderabad, Hdc2A"
    ],
    "Requisition ID": "R91466",
    "Scraped At": "2025-07-29T06:29:01Z",
    "Posted Date Original": "Posted Today"
  },
  {
    "Job ID": "00198848",
    "Title": "GN - SONG - Service - Nice CX One - Senior Manager",
    "Location": "",
    "Posted Date": "2025-07-29T00:00:00Z",
    "Job URL": "https://accenture.wd103.myworkdayjobs.com/en-US/AccentureCareers/job/Pune-PDC2C/GN---SONG---ACE---NICE-Cxone-Manager_R00198848",
    "External Path": "/job/Pune-PDC2C/GN---SONG---ACE---NICE-Cxone-Manager_R00198848",
    "Bullet Fields": [
      "R00198848",
      "Pune, Pdc2C"
    ],
    "Requisition ID": "R00198848",
    "Scraped At": "2025-07-29T06:29:01Z",
    "Posted Date Original": "Posted Today"
  },
  {
    "Job ID": "00279527",
    "Title": "Data Designer",
    "Location": "",
    "Posted Date": "2025-07-29T00:00:00Z",
    "Job URL": "https://accenture.wd103.myworkdayjobs.com/en-US/AccentureCareers/job/Ebene/Data-Designer_R00279527",
    "External Path": "/job/Ebene/Data-Designer_R00279527",
    "Bullet Fields": [
      "R00279527",
      "Ebene"
    ],
    "Requisition ID": "R00279527",
    "Scraped At": "2025-07-29T06:29:01Z",
    "Posted Date Original": "Posted Today"
  },
  {
    "Job ID": "",
    "Title": "",
    "Location": "",
    "Posted Date": "",
    "Job URL": "https://accenture.wd103.myworkdayjobs.com/en-US/AccentureCareers",
    "External Path": "",
    "Bullet Fields": [
      "R00219804",
      "Bengaluru, Bdc7C"
    ],
    "Requisition ID": "R00219804",
    "Scraped At": "2025-07-29T06:29:01Z",
    "Posted Date Original": ""
  },
  {
    "Job ID": "00276936",
    "Title": "Industry X - MES Siemens Opcenter Camstar Senior Manager",
    "Location": "",
    "Posted Date": "2025-07-26T00:00:00Z",
    "Job URL": "https://accenture.wd103.myworkdayjobs.com/en-US/AccentureCareers/job/CA---Mountain-View/Industry-X---MES-Siemens-Opcenter-Camstar-Senior-Manager_R00276936",
    "External Path": "/job/CA---Mountain-View/Industry-X---MES-Siemens-Opcenter-Camstar-Senior-Manager_R00276936",
    "Bullet Fields": [
      "R00276936",
      "Location Negotiable"
    ],
    "Requisition ID": "R00276936",
    "Scraped At": "2025-07-29T06:29:01Z",
    "Posted Date Original": "Posted 3 Days Ago"
  },
  {
    "Job ID": "00276739",
    "Title": "Industry X - MES Siemens Camstar Opcenter Associate Manager/Manager",
    "Location": "",
    "Posted Date": "2025-07-26T00:00:00Z",
    "Job URL": "https://accenture.wd103.myworkdayjobs.com/en-US/AccentureCareers/job/Chicago-Accenture-Tower-Corp/Industry-X---MES-Siemens-Camstar-Opcenter-Associate-Manager-Manager_R00276739",
    "External Path": "/job/Chicago-Accenture-Tower-Corp/Industry-X---MES-Siemens-Camstar-Opcenter-Associate-Manager-Manager_R00276739",
    "Bullet Fields": [
      "R00276739",
      "Location Negotiable"
    ],
    "Requisition ID": "R00276739",
    "Scraped At": "2025-07-29T06:29:01Z",
    "Posted Date Original": "Posted 3 Days Ago"
  },
  {
    "Job ID": "00250139",
    "Title": "Technical AZ -104 Customer Success Solution Specialist | Senior Analyst",
    "Location": "",
    "Posted Date": "2025-07-26T00:00:00Z",
    "Job URL": "https://accenture.wd103.myworkdayjobs.com/en-US/AccentureCareers/job/Heredia/Azure-104-Customer-Success-Solution-Specialist---Senior-Analyst_R00250139",
    "External Path": "/job/Heredia/Azure-104-Customer-Success-Solution-Specialist---Senior-Analyst_R00250139",
    "Bullet Fields": [
      "R00250139",
      "Heredia"
    ],
    "Requisition ID": "R00250139",
    "Scraped At": "2025-07-29T06:29:01Z",
    "Posted Date Original": "Posted 3 Days Ago"
  },
  {
    "Job ID": "00246694",
    "Title": "Stage in area Consulting",
    "Location": "",
    "Posted Date": "2025-07-26T00:00:00Z",
    "Job URL": "https://accenture.wd103.myworkdayjobs.com/en-US/AccentureCareers/job/Milano/Stage-in-area-Consulting--Online---Phone-Recruitment-_R00246694",
    "External Path": "/job/Milano/Stage-in-area-Consulting--Online---Phone-Recruitment-_R00246694",
    "Bullet Fields": [
      "R00246694",
      "Location Negotiable"
    ],
    "Requisition ID": "R00246694",
    "Scraped At": "2025-07-29T06:29:01Z",
    "Posted Date Original": "Posted 3 Days Ago"
  },
  {
    "Job ID": "00277891-1",
    "Title": "Strat Growth Init Counsel Manager",
    "Location": "",
    "Posted Date": "2025-07-26T00:00:00Z",
    "Job URL": "https://accenture.wd103.myworkdayjobs.com/en-US/AccentureCareers/job/Sao-Paulo-Torre-Paineira/Strat-Growth-Init-Counsel-Manager_R00277891-1",
    "External Path": "/job/Sao-Paulo-Torre-Paineira/Strat-Growth-Init-Counsel-Manager_R00277891-1",
    "Bullet Fields": [
      "R00277891",
      "Sao Paulo, Torre Paineira"
    ],
    "Requisition ID": "R00277891",
    "Scraped At": "2025-07-29T06:29:01Z",
    "Posted Date Original": "Posted 3 Days Ago"
  },
  {
    "Job ID": "00273549",
    "Title": "C# Developer - Intern",
    "Location": "",
    "Posted Date": "2025-07-26T00:00:00Z",
    "Job URL": "https://accenture.wd103.myworkdayjobs.com/en-US/AccentureCareers/job/Budapest/C--Developer---Intern_R00273549",
    "External Path": "/job/Budapest/C--Developer---Intern_R00273549",
    "Bullet Fields": [
      "R00273549",
      "Budapest"
    ],
    "Requisition ID": "R00273549",
    "Scraped At": "2025-07-29T06:29:01Z",
    "Posted Date Original": "Posted 3 Days Ago"
  },
  {
    "Job ID": "00237564-14",
    "Title": "S&C-GN - E2E Delivery Lead - Platforms (SAP)_CL6",
    "Location": "",
    "Posted Date": "2025-07-26T00:00:00Z",
    "Job URL": "https://accenture.wd103.myworkdayjobs.com/en-US/AccentureCareers/job/Bengaluru-BDC14A/GN-SAP-Platform---CMT---Delivery-Lead--CL6_R00237564-14",
    "External Path": "/job/Bengaluru-BDC14A/GN-SAP-Platform---CMT---Delivery-Lead--CL6_R00237564-14",
    "Bullet Fields": [
      "R00237564",
      "Bengaluru, Bdc14A"
    ],
    "Requisition ID": "R00237564",
    "Scraped At": "2025-07-29T06:29:01Z",
    "Posted Date Original": "Posted 3 Days Ago"
  },
  {
    "Job ID": "00237502-3",
    "Title": "GN_SAP Platform _ Resources - Cross Functional SME_ CL5",
    "Location": "",
    "Posted Date": "2025-07-26T00:00:00Z",
    "Job URL": "https://accenture.wd103.myworkdayjobs.com/en-US/AccentureCareers/job/Gurugram/GN-SAP-Platform---Resources---Enterprise-SA--CL6_R00237502-3",
    "External Path": "/job/Gurugram/GN-SAP-Platform---Resources---Enterprise-SA--CL6_R00237502-3",
    "Bullet Fields": [
      "R00237502",
      "Gurugram"
    ],
    "Requisition ID": "R00237502",
    "Scraped At": "2025-07-29T06:29:01Z",
    "Posted Date Original": "Posted 3 Days Ago"
  },
  {
    "Job ID": "00237441-56",
    "Title": "S&C-GN - E2E Delivery Lead - Platforms (SAP)_CL6",
    "Location": "",
    "Posted Date": "2025-07-26T00:00:00Z",
    "Job URL": "https://accenture.wd103.myworkdayjobs.com/en-US/AccentureCareers/job/Chennai-CC1A-NonSTPI/GN-SAP-Platform---Products---Delivery-Lead--CL6_R00237441-56",
    "External Path": "/job/Chennai-CC1A-NonSTPI/GN-SAP-Platform---Products---Delivery-Lead--CL6_R00237441-56",
    "Bullet Fields": [
      "R00237441",
      "Chennai, Cc1A, Nonstpi"
    ],
    "Requisition ID": "R00237441",
    "Scraped At": "2025-07-29T06:29:01Z",
    "Posted Date Original": "Posted 3 Days Ago"
  }
]